bauklotz/__init__.py
bauklotz/business/__init__.py
bauklotz/business/filter/__init__.py
bauklotz/business/filter/generic/__init__.py
bauklotz/business/filter/generic/mapping.py
bauklotz/business/filter/generic/predicate.py
bauklotz/business/filter/python/__init__.py
bauklotz/business/filter/python/definition.py
bauklotz/business/filter/python/file.py
bauklotz/business/filter/python/network.py
bauklotz/business/filter/python/project.py
bauklotz/business/filter/python/structure.py
bauklotz/business/pipe/__init__.py
bauklotz/business/pipe/graph.py
bauklotz/configuration/__init__.py
bauklotz/configuration/catalog/__init__.py
bauklotz/configuration/catalog/builtin.py
bauklotz/configuration/catalog/plugin.py
bauklotz/configuration/dsl/__init__.py
bauklotz/configuration/dsl/parser.py
bauklotz/configuration/dsl/tokenizer.py
bauklotz/console.py
bauklotz/reporting/__init__.py
bauklotz/reporting/fact/__init__.py
bauklotz/reporting/item/__init__.py
bauklotz/reporting/item/dependency.py
bauklotz/reporting/item/generic/__init__.py
bauklotz/reporting/item/generic/group.py
bauklotz/reporting/item/graph.py
bauklotz/reporting/item/project.py
bauklotz/reporting/item/python/__init__.py
bauklotz/reporting/item/python/definition.py
bauklotz/reporting/item/python/dependency.py
bauklotz/reporting/item/python/project.py
bauklotz/reporting/logging.py
bauklotz/reporting/report/__init__.py
bauklotz/reporting/report/buffered.py
bauklotz/reporting/report/writer/__init__.py
bauklotz/reporting/report/writer/filesystem.py
bauklotz/reporting/report/writer/graph.py
bauklotz/reporting/report/writer/uml.py
bauklotz/reporting/types.py
bauklotz-1.0.3.dist-info/LICENSE
bauklotz-1.0.3.dist-info/METADATA
bauklotz-1.0.3.dist-info/WHEEL
bauklotz-1.0.3.dist-info/entry_points.txt
bauklotz-1.0.3.dist-info/RECORD
