Metadata-Version: 2.3
Name: bauklotz
Version: 1.0.3
Summary: 
License: BSD3
Keywords: software-architecture,static-analysis,code-analysis,visualization,uml,class-diagram,pipeline,architecture-analysis,plugin-system,python-ast,graph-visualization,metrics,code-quality,documentation-generator,dependency-analysis
Author: voidpointercast
Author-email: voidpointercast@justmail.de
Maintainer: voidpointercast
Maintainer-email: voidpointercast@justmail.de
Requires-Python: >=3.12,<4.0
Classifier: Development Status :: 4 - Beta
Classifier: Intended Audience :: Developers
Classifier: Intended Audience :: Information Technology
Classifier: License :: OSI Approved :: BSD License
Classifier: License :: Other/Proprietary License
Classifier: Natural Language :: English
Classifier: Operating System :: OS Independent
Classifier: Programming Language :: Python :: 3
Classifier: Programming Language :: Python :: 3.12
Classifier: Programming Language :: Python :: 3.13
Classifier: Topic :: Documentation
Classifier: Topic :: Software Development :: Code Generators
Classifier: Topic :: Software Development :: Documentation
Classifier: Topic :: Software Development :: Libraries :: Application Frameworks
Classifier: Topic :: Software Development :: Libraries :: Python Modules
Classifier: Topic :: Software Development :: Quality Assurance
Classifier: Typing :: Typed
Requires-Dist: asteval (>=1.0.6,<2.0.0)
Requires-Dist: dacite (>=1.9.2,<2.0.0)
Requires-Dist: flatten-dict (>=0.4.2,<0.5.0)
Requires-Dist: jinja2 (>=3.1.6,<4.0.0)
Requires-Dist: lark (>=1.2.2,<2.0.0)
Requires-Dist: loguru (>=0.7.3,<0.8.0)
Requires-Dist: more-itertools (>=10.7.0,<11.0.0)
Requires-Dist: networkx (>=3.4.2,<4.0.0)
Requires-Dist: pyyaml (>=6.0.2,<7.0.0)
Requires-Dist: stdlib-list (>=0.11.1,<0.12.0)
Requires-Dist: tabulate (>=0.9.0,<0.10.0)
Requires-Dist: toolz (>=1.0.0,<2.0.0)
Project-URL: Documentation, https://bauklotz.readthedocs.io/
Project-URL: Repository, https://gitlab.com/patrick.daniel.gress/bauklotz
